gone/__about__.py
gone/__init__.py
gone/core.py
gone-0.1.0.dist-info/METADATA
gone-0.1.0.dist-info/WHEEL
gone-0.1.0.dist-info/licenses/LICENSE.txt
gone-0.1.0.dist-info/RECORD
