Metadata-Version: 2.3
Name: gone
Version: 0.1.0
Project-URL: Documentation, https://github.com/Robin van der Noord/gone#readme
Project-URL: Issues, https://github.com/Robin van der Noord/gone/issues
Project-URL: Source, https://github.com/Robin van der Noord/gone
Author-email: Robin van der Noord <robinvandernoord@gmail.com>
License-Expression: MIT
License-File: LICENSE.txt
Classifier: Development Status :: 4 - Beta
Classifier: Programming Language :: Python
Classifier: Programming Language :: Python :: 3.10
Classifier: Programming Language :: Python :: 3.11
Classifier: Programming Language :: Python :: 3.12
Classifier: Programming Language :: Python :: Implementation :: CPython
Classifier: Programming Language :: Python :: Implementation :: PyPy
Requires-Python: >=3.10
Provides-Extra: dev
Requires-Dist: black; extra == 'dev'
Requires-Dist: hatch; extra == 'dev'
Requires-Dist: su6[all]; extra == 'dev'
